LICENSE
MANIFEST.in
README.rst
setup.py
myconnect/__init__.py
myconnect/mypymysql.py
mypymysql/__init__.py
mypymysql/mypymysql.py
mypymysql.egg-info/PKG-INFO
mypymysql.egg-info/SOURCES.txt
mypymysql.egg-info/dependency_links.txt
mypymysql.egg-info/not-zip-safe
mypymysql.egg-info/top_level.txt
mypymysql/__pycache__/mypymysql.cpython-34.pyc