Metadata-Version: 2.1
Name: mypymysql
Version: 1.1
Summary: mypymysql
Home-page: https://markdown.felinae.net
Author: xuzhao
Author-email: markdown@felinae.net
License: UNKNOWN
Keywords: django markdown editor editormd
Platform: UNKNOWN
Classifier: Programming Language :: Python
Classifier: Development Status :: 4 - Beta
Classifier: Operating System :: OS Independent
Classifier: License :: OSI Approved :: Apache Software License
Classifier: Framework :: Django
